menucmd/__init__.py
menucmd/dsl/__init__.py
menucmd/dsl/lines_to_dict.py
menucmd/dsl/parser.py
menucmd/src/__init__.py
menucmd/src/builtins.py
menucmd/src/menucmd.py
menucmd/tests/__init__.py
menucmd/tests/menutesting.py
menucmd/tests/notebook_test.py
menucmd-1.1.2.dist-info/METADATA
menucmd-1.1.2.dist-info/WHEEL
menucmd-1.1.2.dist-info/top_level.txt
menucmd-1.1.2.dist-info/RECORD
