Metadata-Version: 2.1
Name: menucmd
Version: 1.1.2
Summary: Command line menu interface
Home-page: https://github.com/Casey-Litmer/menucmd
Author: Casey Litmer
Author-email: litmerc@msn.com
License: MIT
Classifier: License :: OSI Approved :: MIT License
Classifier: Programming Language :: Python :: 3
Classifier: Operating System :: OS Independent
Requires-Python: >=3.6
Requires-Dist: macrolibs
Requires-Dist: regex
